deepfakebody/__init__.py
deepfakebody/cardiovascular/__init__.py
deepfakebody/cardiovascular/deepfakeecg/__init__.py
deepfakebody/cardiovascular/deepfakeecg/deepfakeecg.py
deepfakebody/digestive/__init__.py
deepfakebody/digestive/gitract/__init__.py
deepfakebody/digestive/gitract/functions.py
deepfakebody-1.0.0.dist-info/LICENSE
deepfakebody-1.0.0.dist-info/METADATA
deepfakebody-1.0.0.dist-info/WHEEL
deepfakebody-1.0.0.dist-info/top_level.txt
deepfakebody-1.0.0.dist-info/RECORD
