Metadata-Version: 2.1
Name: deepfakebody
Version: 1.0.0
Summary: Unlimited medical data generators.
Home-page: https://github.com/vlbthambawita/deepfakebody
Author: Vajira Thambawita
Author-email: vlbthambawita@gmail.com
License: UNKNOWN
Platform: UNKNOWN
Classifier: Programming Language :: Python :: 3
Classifier: License :: OSI Approved :: MIT License
Classifier: Operating System :: OS Independent
Requires-Python: >=3.6
Requires-Dist: deepfake-gitract
